{
  "type": "Feature",
  "properties": {
    "iso:country":"SG",
    "sg:address":"391B Orchard Road #23-01 Ngee Ann City Tower B",
    "sg:classifiers":[
        {
            "category":"Professional",
            "subcategory":"Computer Services",
            "type":"Services"
        }
    ],
    "sg:postcode":"238874",
    "sg:tags":[
        "-agriculture-physical-commodity-management",
        "aviation-fuel-risk-management",
        "rightangle",
        "coal-supply-and-trade-management-software",
        "commodity-scheduling-software",
        "energy-commodity-management-software-solution",
        "enterprise-trade-and-risk-management-solution"
    ],
    "sg:website":"http://www.solarc.com/index.html",
    "wof:name":"SolArc",
    "wof:placetype":"venue"
},
  "geometry": {"coordinates":[103.835307,1.303132],"type":"Point"}
}