{
  "type": "Feature",
  "properties": {
    "iso:country":"SG",
    "sg:address":"3791 Jalan Bukit Merah 10-17 E-Centre@Redhill",
    "sg:city":"Singapore",
    "sg:classifiers":[
        {
            "category":"Professional",
            "subcategory":"Computer Services",
            "type":"Services"
        }
    ],
    "sg:postcode":"159471",
    "sg:tags":[
        "after-sales",
        "repairs",
        "warranty"
    ],
    "sg:website":"http://www.yarraa.com",
    "wof:name":"Yarraa",
    "wof:placetype":"venue"
},
  "geometry": {"coordinates":[103.8116284,1.2850793],"type":"Point"}
}